delphai_company_pages/__init__.py
delphai_company_pages/pages.py
delphai_company_pages/test_pages.py
delphai_company_pages-0.1.9.dist-info/WHEEL
delphai_company_pages-0.1.9.dist-info/METADATA
delphai_company_pages-0.1.9.dist-info/RECORD
