Metadata-Version: 2.1
Name: delphai-company-pages
Version: 0.1.9
Summary: 
Author: delphai
Author-email: admin@delphai.com
Requires-Python: >=3.8,<4.0
Classifier: Programming Language :: Python :: 3
Classifier: Programming Language :: Python :: 3.8
Requires-Dist: aiohttp (>=3.7.4,<4.0.0)
Requires-Dist: azure-storage-blob (>=12.8.0,<13.0.0)
Requires-Dist: networkx (>=2.5,<3.0)
Requires-Dist: warcio (>=1.7.4,<2.0.0)
